{
   "cs-group-4-Pierre-dynamodb": [
       {
               "PutRequest": {
                   "Item": {
                       "type": {"S":"movie"},
                       "uuid": {"S":"Addiction, The (1995)"},
                       "genre": {"S":"Drama|Horror"},
                       "movie_ratings": {"S":"{\"380\": \"1.0\", \"571\": \"2.0\"}"}
                   }
               }
           },
       {
               "PutRequest": {
                   "Item": {
                       "type": {"S":"movie"},
                       "uuid": {"S":"Batman Forever (1995)"},
                       "genre": {"S":"Action|Adventure|Comedy|Crime"},
                       "movie_ratings": {"S":"{\"5\": \"3.0\", \"6\": \"3.0\", \"8\": \"2.0\", \"11\": \"3.0\", \"14\": \"2.0\", \"19\": \"2.0\", \"26\": \"3.0\", \"32\": \"3.0\", \"37\": \"3.0\", \"38\": \"3.0\", \"40\": \"3.0\", \"42\": \"2.0\", \"43\": \"5.0\", \"46\": \"4.0\", \"56\": \"4.0\", \"57\": \"2.0\", \"58\": \"3.0\", \"63\": \"1.0\", \"64\": \"2.5\", \"68\": \"3.0\", \"81\": \"3.0\", \"82\": \"3.0\", \"91\": \"2.0\", \"93\": \"4.0\", \"94\": \"3.0\", \"99\": \"5.0\", \"102\": \"3.0\", \"107\": \"3.0\", \"109\": \"3.0\", \"115\": \"3.0\", \"117\": \"3.0\", \"118\": \"2.0\", \"126\": \"4.0\", \"130\": \"4.0\", \"133\": \"1.0\", \"134\": \"4.0\", \"135\": \"1.0\", \"136\": \"3.0\", \"144\": \"3.0\", \"145\": \"3.0\", \"153\": \"0.5\", \"155\": \"3.0\", \"160\": \"3.0\", \"162\": \"4.0\", \"166\": \"2.5\", \"170\": \"3.0\", \"173\": \"3.0\", \"174\": \"3.0\", \"176\": \"3.0\", \"177\": \"3.0\", \"179\": \"3.0\", \"182\": \"3.5\", \"191\": \"1.0\", \"197\": \"2.0\", \"201\": \"4.0\", \"210\": \"3.5\", \"217\": \"2.0\", \"219\": \"2.5\", \"226\": \"4.0\", \"229\": \"3.0\", \"230\": \"3.5\", \"234\": \"5.0\", \"235\": \"3.0\", \"240\": \"3.0\", \"242\": \"2.0\", \"243\": \"4.0\", \"259\": \"4.0\", \"274\": \"3.5\", \"284\": \"3.0\", \"288\": \"2.0\", \"292\": \"3.0\", \"294\": \"3.0\", \"298\": \"2.0\", \"304\": \"3.0\", \"307\": \"2.0\", \"314\": \"2.0\", \"318\": \"3.0\", \"321\": \"5.0\", \"323\": \"2.0\", \"330\": \"3.0\", \"340\": \"4.0\", \"347\": \"3.0\", \"353\": \"3.0\", \"357\": \"2.5\", \"373\": \"3.0\", \"374\": \"4.0\", \"379\": \"3.0\", \"380\": \"3.0\", \"385\": \"3.0\", \"386\": \"2.0\", \"387\": \"3.0\", \"394\": \"3.0\", \"414\": \"2.0\", \"432\": \"3.5\", \"437\": \"1.0\", \"438\": \"3.0\", \"446\": \"1.0\", \"447\": \"4.0\", \"448\": \"2.5\", \"452\": \"4.0\", \"458\": \"5.0\", \"468\": \"3.0\", \"470\": \"4.0\", \"474\": \"3.0\", \"476\": \"3.0\", \"480\": \"1.0\", \"483\": \"2.0\", \"486\": \"5.0\", \"489\": \"3.0\", \"498\": \"3.0\", \"507\": \"3.0\", \"509\": \"2.0\", \"524\": \"3.0\", \"534\": \"3.5\", \"541\": \"3.0\", \"555\": \"3.0\", \"559\": \"3.0\", \"565\": \"2.0\", \"569\": \"5.0\", \"570\": \"2.5\", \"573\": \"1.5\", \"574\": \"3.0\", \"580\": \"2.0\", \"584\": \"3.0\", \"587\": \"3.0\", \"590\": \"2.5\", \"592\": \"3.0\", \"596\": \"2.5\", \"597\": \"3.0\", \"599\": \"2.0\", \"602\": \"4.0\", \"603\": \"1.0\", \"604\": \"3.0\", \"605\": \"4.0\", \"607\": \"3.0\", \"608\": \"2.5\", \"610\": \"3.0\"}"}
                   }
               }
           },
       {
               "PutRequest": {
                   "Item": {
                       "type": {"S":"movie"},
                       "uuid": {"S":"Beauty of the Day (Belle de jour) (1967)"},
                       "genre": {"S":"Drama"},
                       "movie_ratings": {"S":"{\"84\": \"3.0\", \"109\": \"3.0\", \"156\": \"5.0\", \"177\": \"4.0\", \"221\": \"4.0\", \"260\": \"4.5\", \"315\": \"4.0\", \"318\": \"3.0\", \"387\": \"4.0\", \"391\": \"4.0\", \"410\": \"4.0\", \"606\": \"4.0\"}"}
                   }
               }
           },
       {
               "PutRequest": {
                   "Item": {
                       "type": {"S":"movie"},
                       "uuid": {"S":"Beyond Rangoon (1995)"},
                       "genre": {"S":"Adventure|Drama|War"},
                       "movie_ratings": {"S":"{\"191\": \"4.0\", \"268\": \"1.0\", \"414\": \"2.0\", \"437\": \"4.0\", \"555\": \"1.0\", \"599\": \"2.5\"}"}
                   }
               }
           },
       {
               "PutRequest": {
                   "Item": {
                       "type": {"S":"movie"},
                       "uuid": {"S":"Blue in the Face (1995)"},
                       "genre": {"S":"Comedy|Drama"},
                       "movie_ratings": {"S":"{\"108\": \"4.0\", \"603\": \"2.0\", \"606\": \"4.0\"}"}
                   }
               }
           },
       {
               "PutRequest": {
                   "Item": {
                       "type": {"S":"movie"},
                       "uuid": {"S":"Canadian Bacon (1995)"},
                       "genre": {"S":"Comedy|War"},
                       "movie_ratings": {"S":"{\"1\": \"5.0\", \"135\": \"2.0\", \"181\": \"2.0\", \"217\": \"2.0\", \"294\": \"3.0\", \"307\": \"2.0\", \"372\": \"3.0\", \"391\": \"3.0\", \"414\": \"4.0\", \"599\": \"1.5\", \"606\": \"4.0\"}"}
                   }
               }
           },
       {
               "PutRequest": {
                   "Item": {
                       "type": {"S":"movie"},
                       "uuid": {"S":"Casper (1995)"},
                       "genre": {"S":"Adventure|Children"},
                       "movie_ratings": {"S":"{\"6\": \"4.0\", \"15\": \"1.0\", \"19\": \"3.0\", \"20\": \"3.0\", \"27\": \"2.0\", \"40\": \"4.0\", \"43\": \"5.0\", \"57\": \"1.0\", \"68\": \"3.0\", \"76\": \"0.5\", \"82\": \"1.0\", \"91\": \"2.0\", \"93\": \"4.0\", \"102\": \"3.0\", \"103\": \"3.5\", \"117\": \"3.0\", \"132\": \"2.0\", \"136\": \"3.0\", \"160\": \"3.0\", \"174\": \"3.0\", \"177\": \"3.0\", \"191\": \"2.0\", \"217\": \"2.0\", \"226\": \"2.0\", \"234\": \"5.0\", \"240\": \"4.0\", \"249\": \"3.0\", \"274\": \"3.5\", \"286\": \"3.0\", \"288\": \"2.0\", \"307\": \"1.5\", \"316\": \"2.5\", \"321\": \"3.0\", \"323\": \"3.0\", \"353\": \"3.0\", \"356\": \"3.0\", \"373\": \"3.0\", \"380\": \"3.0\", \"395\": \"3.0\", \"411\": \"3.0\", \"414\": \"2.0\", \"431\": \"1.0\", \"435\": \"4.0\", \"436\": \"3.0\", \"448\": \"3.0\", \"476\": \"3.0\", \"477\": \"0.5\", \"480\": \"2.5\", \"483\": \"2.0\", \"495\": \"3.5\", \"517\": \"2.0\", \"525\": \"3.5\", \"534\": \"4.0\", \"538\": \"4.5\", \"546\": \"2.0\", \"584\": \"5.0\", \"592\": \"4.0\", \"594\": \"4.5\", \"599\": \"1.0\", \"602\": \"3.0\", \"604\": \"4.0\", \"608\": \"0.5\"}"}
                   }
               }
           },
       {
               "PutRequest": {
                   "Item": {
                       "type": {"S":"movie"},
                       "uuid": {"S":"Clockers (1995)"},
                       "genre": {"S":"Crime|Drama|Mystery"},
                       "movie_ratings": {"S":"{\"6\": \"3.0\", \"40\": \"3.0\", \"64\": \"3.5\", \"191\": \"1.0\", \"318\": \"4.0\", \"372\": \"2.0\", \"411\": \"3.0\", \"414\": \"2.0\", \"425\": \"4.5\", \"437\": \"3.0\", \"597\": \"2.0\", \"599\": \"2.5\", \"606\": \"3.5\", \"610\": \"3.5\"}"}
                   }
               }
           },
       {
               "PutRequest": {
                   "Item": {
                       "type": {"S":"movie"},
                       "uuid": {"S":"Congo (1995)"},
                       "genre": {"S":"Action|Adventure|Mystery|Sci-Fi"},
                       "movie_ratings": {"S":"{\"6\": \"5.0\", \"46\": \"4.0\", \"56\": \"3.0\", \"57\": \"1.0\", \"64\": \"2.5\", \"68\": \"2.5\", \"71\": \"3.0\", \"91\": \"2.0\", \"94\": \"3.0\", \"99\": \"2.0\", \"102\": \"3.0\", \"107\": \"4.0\", \"116\": \"4.0\", \"117\": \"3.0\", \"129\": \"3.5\", \"134\": \"3.0\", \"136\": \"3.0\", \"174\": \"3.0\", \"191\": \"1.0\", \"192\": \"4.0\", \"201\": \"4.0\", \"217\": \"3.0\", \"226\": \"3.0\", \"240\": \"4.0\", \"321\": \"4.0\", \"347\": \"3.0\", \"353\": \"2.0\", \"368\": \"2.0\", \"373\": \"1.0\", \"380\": \"3.0\", \"386\": \"3.0\", \"395\": \"4.0\", \"411\": \"3.0\", \"414\": \"1.0\", \"425\": \"3.0\", \"428\": \"1.5\", \"446\": \"3.0\", \"447\": \"2.0\", \"468\": \"2.0\", \"474\": \"1.0\", \"480\": \"2.5\", \"483\": \"3.5\", \"484\": \"4.5\", \"489\": \"1.0\", \"495\": \"3.0\", \"512\": \"4.0\", \"534\": \"3.5\", \"555\": \"2.0\", \"559\": \"2.0\", \"570\": \"2.5\", \"584\": \"5.0\", \"592\": \"3.0\", \"594\": \"5.0\", \"599\": \"2.5\", \"600\": \"2.5\", \"602\": \"3.0\", \"608\": \"2.5\"}"}
                   }
               }
           },
       {
               "PutRequest": {
                   "Item": {
                       "type": {"S":"movie"},
                       "uuid": {"S":"Crimson Tide (1995)"},
                       "genre": {"S":"Drama|Thriller|War"},
                       "movie_ratings": {"S":"{\"6\": \"3.0\", \"19\": \"2.0\", \"28\": \"3.0\", \"33\": \"3.0\", \"38\": \"4.0\", \"42\": \"3.0\", \"43\": \"4.0\", \"46\": \"3.0\", \"54\": \"3.0\", \"56\": \"4.0\", \"58\": \"4.0\", \"81\": \"3.0\", \"83\": \"3.5\", \"84\": \"3.0\", \"91\": \"3.5\", \"94\": \"4.0\", \"99\": \"3.0\", \"102\": \"3.0\", \"107\": \"4.0\", \"109\": \"3.0\", \"112\": \"1.5\", \"116\": \"4.5\", \"117\": \"3.0\", \"121\": \"3.0\", \"126\": \"3.0\", \"130\": \"4.0\", \"134\": \"4.0\", \"135\": \"5.0\", \"136\": \"4.0\", \"140\": \"4.0\", \"142\": \"5.0\", \"145\": \"4.0\", \"170\": \"4.0\", \"174\": \"3.0\", \"176\": \"4.0\", \"177\": \"3.5\", \"178\": \"4.5\", \"179\": \"5.0\", \"181\": \"4.0\", \"182\": \"3.0\", \"191\": \"2.0\", \"195\": \"4.0\", \"199\": \"3.5\", \"202\": \"4.0\", \"235\": \"3.0\", \"240\": \"4.0\", \"242\": \"4.0\", \"243\": \"5.0\", \"288\": \"3.0\", \"292\": \"4.0\", \"297\": \"2.0\", \"308\": \"1.0\", \"314\": \"2.0\", \"321\": \"3.0\", \"323\": \"4.0\", \"340\": \"4.0\", \"349\": \"4.0\", \"353\": \"5.0\", \"368\": \"4.0\", \"372\": \"4.0\", \"374\": \"4.0\", \"376\": \"5.0\", \"379\": \"4.0\", \"386\": \"3.0\", \"404\": \"4.0\", \"411\": \"4.0\", \"414\": \"3.0\", \"425\": \"3.5\", \"429\": \"5.0\", \"436\": \"4.0\", \"448\": \"4.0\", \"455\": \"4.0\", \"458\": \"5.0\", \"468\": \"2.0\", \"470\": \"3.0\", \"474\": \"3.5\", \"476\": \"4.0\", \"480\": \"3.5\", \"485\": \"5.0\", \"486\": \"5.0\", \"489\": \"3.0\", \"498\": \"5.0\", \"512\": \"4.0\", \"514\": \"4.0\", \"524\": \"5.0\", \"530\": \"3.0\", \"541\": \"5.0\", \"552\": \"2.5\", \"559\": \"3.0\", \"566\": \"4.0\", \"570\": \"3.0\", \"572\": \"3.0\", \"574\": \"4.0\", \"584\": \"5.0\", \"586\": \"4.5\", \"588\": \"4.0\", \"589\": \"3.0\", \"590\": \"4.0\", \"592\": \"4.0\", \"599\": \"3.5\", \"600\": \"1.0\", \"602\": \"4.0\", \"609\": \"3.0\"}"}
                   }
               }
           },
       {
               "PutRequest": {
                   "Item": {
                       "type": {"S":"movie"},
                       "uuid": {"S":"Crumb (1994)"},
                       "genre": {"S":"Documentary"},
                       "movie_ratings": {"S":"{\"4\": \"5.0\", \"57\": \"4.0\", \"95\": \"5.0\", \"182\": \"3.5\", \"191\": \"5.0\", \"221\": \"4.5\", \"245\": \"3.0\", \"260\": \"4.5\", \"275\": \"5.0\", \"318\": \"3.5\", \"387\": \"4.0\", \"412\": \"4.0\", \"414\": \"4.0\", \"462\": \"4.0\", \"474\": \"3.5\", \"514\": \"4.0\", \"603\": \"5.0\"}"}
                   }
               }
           },
       {
               "PutRequest": {
                   "Item": {
                       "type": {"S":"movie"},
                       "uuid": {"S":"Desperado (1995)"},
                       "genre": {"S":"Action|Romance|Western"},
                       "movie_ratings": {"S":"{\"1\": \"5.0\", \"6\": \"3.0\", \"18\": \"4.0\", \"34\": \"3.0\", \"38\": \"1.0\", \"40\": \"5.0\", \"42\": \"3.0\", \"64\": \"3.5\", \"68\": \"4.5\", \"82\": \"4.0\", \"91\": \"5.0\", \"99\": \"5.0\", \"102\": \"3.0\", \"109\": \"3.0\", \"121\": \"4.0\", \"132\": \"2.0\", \"134\": \"3.0\", \"136\": \"1.0\", \"140\": \"3.0\", \"144\": \"4.0\", \"147\": \"4.5\", \"171\": \"5.0\", \"181\": \"2.0\", \"182\": \"3.5\", \"194\": \"3.0\", \"238\": \"4.0\", \"239\": \"4.5\", \"244\": \"3.0\", \"246\": \"4.5\", \"256\": \"4.0\", \"263\": \"4.0\", \"274\": \"3.5\", \"298\": \"2.5\", \"305\": \"5.0\", \"313\": \"3.0\", \"314\": \"3.0\", \"335\": \"4.0\", \"336\": \"5.0\", \"353\": \"3.0\", \"368\": \"3.0\", \"372\": \"3.0\", \"373\": \"1.0\", \"380\": \"5.0\", \"386\": \"4.0\", \"387\": \"4.0\", \"414\": \"4.0\", \"428\": \"3.0\", \"431\": \"3.0\", \"434\": \"3.0\", \"435\": \"3.5\", \"448\": \"3.5\", \"452\": \"4.0\", \"453\": \"4.0\", \"480\": \"3.0\", \"486\": \"4.0\", \"493\": \"4.0\", \"541\": \"2.0\", \"560\": \"3.5\", \"573\": \"5.0\", \"588\": \"3.0\", \"590\": \"3.0\", \"592\": \"5.0\", \"599\": \"3.5\", \"602\": \"3.0\", \"603\": \"5.0\", \"608\": \"3.0\"}"}
                   }
               }
           },
       {
               "PutRequest": {
                   "Item": {
                       "type": {"S":"movie"},
                       "uuid": {"S":"Devil in a Blue Dress (1995)"},
                       "genre": {"S":"Crime|Film-Noir|Mystery|Thriller"},
                       "movie_ratings": {"S":"{\"79\": \"5.0\", \"84\": \"4.0\", \"140\": \"3.0\", \"217\": \"3.0\", \"262\": \"3.0\", \"297\": \"2.0\", \"368\": \"3.0\", \"372\": \"3.0\", \"410\": \"3.0\", \"429\": \"3.0\", \"465\": \"4.0\", \"599\": \"2.5\", \"602\": \"4.0\", \"603\": \"4.0\"}"}
                   }
               }
           },
       {
               "PutRequest": {
                   "Item": {
                       "type": {"S":"movie"},
                       "uuid": {"S":"Die Hard: With a Vengeance (1995)"},
                       "genre": {"S":"Action|Crime|Thriller"},
                       "movie_ratings": {"S":"{\"6\": \"3.0\", \"7\": \"4.0\", \"11\": \"3.0\", \"18\": \"4.0\", \"19\": \"3.0\", \"21\": \"3.5\", \"24\": \"3.5\", \"26\": \"4.0\", \"29\": \"4.0\", \"31\": \"4.0\", \"37\": \"5.0\", \"40\": \"4.0\", \"42\": \"2.0\", \"43\": \"5.0\", \"45\": \"5.0\", \"46\": \"4.0\", \"50\": \"3.0\", \"56\": \"3.0\", \"58\": \"4.0\", \"63\": \"4.0\", \"68\": \"3.5\", \"71\": \"5.0\", \"72\": \"4.0\", \"78\": \"3.0\", \"81\": \"3.0\", \"82\": \"4.0\", \"84\": \"3.0\", \"86\": \"4.0\", \"91\": \"3.0\", \"94\": \"4.0\", \"99\": \"5.0\", \"102\": \"3.0\", \"107\": \"3.0\", \"109\": \"3.0\", \"116\": \"3.5\", \"117\": \"3.0\", \"122\": \"5.0\", \"126\": \"4.0\", \"130\": \"4.0\", \"135\": \"1.0\", \"136\": \"5.0\", \"140\": \"4.0\", \"142\": \"3.0\", \"145\": \"3.0\", \"160\": \"3.0\", \"174\": \"3.0\", \"176\": \"4.0\", \"179\": \"4.0\", \"181\": \"3.0\", \"182\": \"3.0\", \"195\": \"2.0\", \"200\": \"4.0\", \"217\": \"3.0\", \"219\": \"4.5\", \"220\": \"4.0\", \"222\": \"3.0\", \"229\": \"3.0\", \"232\": \"3.5\", \"240\": \"5.0\", \"243\": \"5.0\", \"244\": \"2.0\", \"268\": \"2.0\", \"274\": \"4.0\", \"284\": \"5.0\", \"286\": \"4.0\", \"292\": \"3.5\", \"297\": \"3.0\", \"298\": \"3.0\", \"301\": \"2.0\", \"304\": \"4.0\", \"307\": \"2.5\", \"313\": \"3.0\", \"314\": \"2.0\", \"318\": \"3.5\", \"321\": \"3.0\", \"326\": \"4.0\", \"340\": \"4.0\", \"347\": \"3.0\", \"349\": \"4.0\", \"353\": \"5.0\", \"354\": \"4.0\", \"368\": \"2.0\", \"369\": \"3.5\", \"372\": \"4.0\", \"374\": \"3.0\", \"376\": \"3.5\", \"379\": \"2.0\", \"380\": \"5.0\", \"386\": \"2.0\", \"391\": \"2.0\", \"395\": \"3.0\", \"402\": \"5.0\", \"404\": \"3.0\", \"408\": \"3.5\", \"411\": \"3.0\", \"414\": \"3.0\", \"425\": \"3.5\", \"428\": \"1.0\", \"429\": \"4.0\", \"432\": \"2.0\", \"436\": \"3.0\", \"438\": \"4.0\", \"446\": \"3.0\", \"447\": \"4.0\", \"448\": \"4.0\", \"453\": \"5.0\", \"455\": \"3.0\", \"458\": \"4.0\", \"464\": \"5.0\", \"468\": \"3.0\", \"470\": \"3.0\", \"475\": \"4.5\", \"476\": \"3.0\", \"480\": \"3.0\", \"483\": \"4.5\", \"485\": \"5.0\", \"486\": \"3.0\", \"489\": \"3.0\", \"507\": \"3.0\", \"512\": \"5.0\", \"517\": \"2.5\", \"524\": \"3.0\", \"534\": \"4.5\", \"536\": \"2.0\", \"541\": \"3.0\", \"543\": \"5.0\", \"553\": \"4.5\", \"557\": \"5.0\", \"559\": \"3.0\", \"565\": \"3.0\", \"566\": \"3.0\", \"569\": \"5.0\", \"570\": \"4.0\", \"573\": \"5.0\", \"584\": \"5.0\", \"588\": \"4.0\", \"590\": \"3.0\", \"592\": \"3.0\", \"594\": \"4.5\", \"599\": \"3.0\", \"600\": \"2.5\", \"602\": \"5.0\", \"604\": \"4.0\", \"607\": \"4.0\"}"}
                   }
               }
           },
       {
               "PutRequest": {
                   "Item": {
                       "type": {"S":"movie"},
                       "uuid": {"S":"Doom Generation, The (1995)"},
                       "genre": {"S":"Comedy|Crime|Drama"},
                       "movie_ratings": {"S":"{\"182\": \"1.5\", \"414\": \"3.0\", \"603\": \"4.0\"}"}
                   }
               }
           },
       {
               "PutRequest": {
                   "Item": {
                       "type": {"S":"movie"},
                       "uuid": {"S":"First Knight (1995)"},
                       "genre": {"S":"Action|Drama|Romance"},
                       "movie_ratings": {"S":"{\"6\": \"5.0\", \"12\": \"5.0\", \"38\": \"4.0\", \"40\": \"2.0\", \"42\": \"3.0\", \"43\": \"5.0\", \"48\": \"3.5\", \"58\": \"5.0\", \"68\": \"3.0\", \"75\": \"4.0\", \"93\": \"4.0\", \"99\": \"5.0\", \"100\": \"4.5\", \"109\": \"3.0\", \"117\": \"3.0\", \"136\": \"4.0\", \"147\": \"0.5\", \"162\": \"3.0\", \"170\": \"4.0\", \"176\": \"5.0\", \"181\": \"3.0\", \"194\": \"3.5\", \"240\": \"5.0\", \"284\": \"1.0\", \"287\": \"1.5\", \"303\": \"3.0\", \"304\": \"4.0\", \"316\": \"1.5\", \"336\": \"4.0\", \"337\": \"4.0\", \"353\": \"3.0\", \"356\": \"3.0\", \"368\": \"2.0\", \"373\": \"2.0\", \"395\": \"3.0\", \"414\": \"2.0\", \"428\": \"2.0\", \"429\": \"5.0\", \"432\": \"4.5\", \"437\": \"2.0\", \"438\": \"3.5\", \"446\": \"1.0\", \"447\": \"4.0\", \"480\": \"2.5\", \"488\": \"1.5\", \"489\": \"0.5\", \"524\": \"2.0\", \"559\": \"3.0\", \"586\": \"3.5\", \"590\": \"3.0\", \"599\": \"1.5\", \"604\": \"3.0\", \"606\": \"2.5\", \"608\": \"0.5\"}"}
                   }
               }
           },
       {
               "PutRequest": {
                   "Item": {
                       "type": {"S":"movie"},
                       "uuid": {"S":"Free Willy 2: The Adventure Home (1995)"},
                       "genre": {"S":"Adventure|Children|Drama"},
                       "movie_ratings": {"S":"{\"181\": \"3.0\", \"234\": \"2.0\", \"240\": \"3.0\", \"373\": \"2.0\", \"428\": \"0.5\", \"429\": \"3.0\", \"436\": \"3.0\", \"460\": \"1.0\", \"534\": \"3.5\", \"604\": \"3.0\"}"}
                   }
               }
           },
       {
               "PutRequest": {
                   "Item": {
                       "type": {"S":"movie"},
                       "uuid": {"S":"Hackers (1995)"},
                       "genre": {"S":"Action|Adventure|Crime|Thriller"},
                       "movie_ratings": {"S":"{\"6\": \"3.0\", \"11\": \"4.0\", \"19\": \"3.0\", \"21\": \"2.0\", \"29\": \"3.0\", \"51\": \"4.0\", \"68\": \"2.5\", \"82\": \"3.0\", \"119\": \"5.0\", \"132\": \"3.0\", \"136\": \"4.0\", \"181\": \"3.0\", \"182\": \"2.5\", \"217\": \"3.0\", \"226\": \"5.0\", \"230\": \"3.0\", \"256\": \"4.5\", \"274\": \"2.5\", \"294\": \"2.0\", \"297\": \"1.0\", \"313\": \"3.0\", \"368\": \"2.0\", \"387\": \"3.0\", \"411\": \"3.0\", \"414\": \"3.0\", \"416\": \"2.5\", \"438\": \"4.0\", \"448\": \"3.0\", \"452\": \"4.0\", \"483\": \"4.0\", \"554\": \"5.0\", \"599\": \"3.0\", \"602\": \"3.0\", \"604\": \"3.0\", \"608\": \"4.5\"}"}
                   }
               }
           },
       {
               "PutRequest": {
                   "Item": {
                       "type": {"S":"movie"},
                       "uuid": {"S":"Jeffrey (1995)"},
                       "genre": {"S":"Comedy|Drama"},
                       "movie_ratings": {"S":"{\"4\": \"3.0\", \"6\": \"3.0\", \"57\": \"4.0\", \"173\": \"5.0\", \"273\": \"5.0\", \"602\": \"3.0\"}"}
                   }
               }
           },
       {
               "PutRequest": {
                   "Item": {
                       "type": {"S":"movie"},
                       "uuid": {"S":"Johnny Mnemonic (1995)"},
                       "genre": {"S":"Action|Sci-Fi|Thriller"},
                       "movie_ratings": {"S":"{\"15\": \"1.0\", \"28\": \"3.0\", \"40\": \"4.0\", \"45\": \"3.0\", \"48\": \"3.5\", \"66\": \"3.5\", \"91\": \"4.5\", \"102\": \"3.0\", \"117\": \"3.0\", \"136\": \"1.0\", \"149\": \"3.0\", \"181\": \"1.0\", \"182\": \"3.5\", \"198\": \"4.0\", \"217\": \"3.0\", \"218\": \"2.0\", \"219\": \"2.5\", \"234\": \"2.0\", \"240\": \"5.0\", \"243\": \"5.0\", \"256\": \"4.0\", \"274\": \"2.5\", \"284\": \"3.0\", \"297\": \"1.0\", \"304\": \"2.0\", \"313\": \"1.0\", \"314\": \"1.0\", \"323\": \"1.5\", \"353\": \"2.0\", \"368\": \"2.0\", \"380\": \"4.0\", \"385\": \"3.0\", \"386\": \"2.0\", \"395\": \"4.0\", \"404\": \"3.0\", \"414\": \"3.0\", \"425\": \"3.5\", \"431\": \"2.0\", \"446\": \"2.0\", \"448\": \"2.0\", \"480\": \"2.5\", \"483\": \"3.5\", \"489\": \"0.5\", \"524\": \"3.0\", \"555\": \"2.0\", \"580\": \"3.5\", \"599\": \"2.0\", \"600\": \"2.0\", \"602\": \"3.0\", \"603\": \"2.0\", \"604\": \"2.0\", \"606\": \"3.0\", \"608\": \"4.0\"}"}
                   }
               }
           },
       {
               "PutRequest": {
                   "Item": {
                       "type": {"S":"movie"},
                       "uuid": {"S":"Judge Dredd (1995)"},
                       "genre": {"S":"Action|Crime|Sci-Fi"},
                       "movie_ratings": {"S":"{\"19\": \"1.0\", \"40\": \"4.0\", \"42\": \"2.0\", \"43\": \"3.0\", \"45\": \"1.0\", \"46\": \"5.0\", \"56\": \"3.0\", \"58\": \"2.0\", \"61\": \"3.0\", \"68\": \"2.5\", \"75\": \"3.0\", \"91\": \"3.5\", \"93\": \"4.0\", \"102\": \"2.0\", \"109\": \"2.0\", \"119\": \"3.0\", \"134\": \"3.0\", \"136\": \"3.0\", \"149\": \"2.0\", \"160\": \"3.0\", \"167\": \"2.5\", \"182\": \"3.5\", \"217\": \"2.0\", \"219\": \"2.5\", \"222\": \"3.0\", \"240\": \"3.0\", \"243\": \"3.0\", \"256\": \"5.0\", \"274\": \"3.5\", \"284\": \"4.0\", \"294\": \"3.0\", \"298\": \"2.0\", \"304\": \"3.0\", \"314\": \"3.0\", \"323\": \"3.0\", \"330\": \"1.0\", \"353\": \"3.0\", \"368\": \"2.0\", \"373\": \"1.0\", \"380\": \"4.0\", \"386\": \"2.0\", \"395\": \"4.0\", \"414\": \"3.0\", \"428\": \"3.0\", \"438\": \"2.5\", \"444\": \"2.0\", \"480\": \"2.0\", \"483\": \"1.0\", \"486\": \"4.0\", \"495\": \"0.5\", \"524\": \"1.0\", \"534\": \"4.0\", \"552\": \"1.0\", \"555\": \"1.0\", \"559\": \"3.0\", \"584\": \"4.0\", \"592\": \"3.0\", \"597\": \"1.0\", \"599\": \"2.5\", \"602\": \"3.0\", \"604\": \"3.0\", \"608\": \"3.0\"}"}
                   }
               }
           },
       {
               "PutRequest": {
                   "Item": {
                       "type": {"S":"movie"},
                       "uuid": {"S":"Jury Duty (1995)"},
                       "genre": {"S":"Comedy"},
                       "movie_ratings": {"S":"{\"6\": \"3.0\", \"43\": \"5.0\", \"136\": \"3.0\", \"217\": \"2.0\", \"240\": \"5.0\", \"274\": \"3.5\", \"414\": \"1.0\", \"436\": \"2.0\", \"559\": \"1.0\", \"608\": \"1.5\"}"}
                   }
               }
           },
       {
               "PutRequest": {
                   "Item": {
                       "type": {"S":"movie"},
                       "uuid": {"S":"Kids (1995)"},
                       "genre": {"S":"Drama"},
                       "movie_ratings": {"S":"{\"23\": \"3.0\", \"109\": \"5.0\", \"124\": \"4.0\", \"132\": \"3.0\", \"191\": \"5.0\", \"274\": \"3.0\", \"307\": \"3.5\", \"387\": \"4.0\", \"414\": \"4.0\", \"415\": \"4.0\", \"419\": \"4.0\", \"424\": \"4.5\", \"437\": \"5.0\", \"484\": \"4.5\", \"503\": \"4.5\", \"585\": \"3.5\", \"588\": \"4.0\", \"599\": \"2.5\", \"603\": \"5.0\", \"606\": \"3.5\"}"}
                   }
               }
           },
       {
               "PutRequest": {
                   "Item": {
                       "type": {"S":"movie"},
                       "uuid": {"S":"Living in Oblivion (1995)"},
                       "genre": {"S":"Comedy"},
                       "movie_ratings": {"S":"{\"4\": \"5.0\", \"95\": \"4.0\", \"171\": \"5.0\", \"182\": \"4.5\", \"275\": \"4.0\", \"318\": \"3.5\", \"414\": \"4.0\", \"437\": \"5.0\", \"477\": \"4.0\", \"500\": \"5.0\", \"597\": \"4.0\", \"602\": \"4.0\", \"603\": \"4.0\"}"}
                   }
               }
           },
       {
               "PutRequest": {
                   "Item": {
                       "type": {"S":"movie"},
                       "uuid": {"S":"Lord of Illusions (1995)"},
                       "genre": {"S":"Horror"},
                       "movie_ratings": {"S":"{\"6\": \"3.0\", \"51\": \"4.0\", \"136\": \"3.0\", \"312\": \"3.0\", \"314\": \"1.0\", \"387\": \"3.0\", \"592\": \"1.0\", \"604\": \"4.0\"}"}
                   }
               }
           }
   ]
}