{
   "cs-group-4-Pierre-dynamodb": [
       {
               "PutRequest": {
                   "Item": {
                       "type": {"S":"movie"},
                       "uuid": {"S":"Losin\" It (1983)"},
                       "genre": {"S":"Comedy"},
                       "movie_ratings": {"S":"{\"474\": \"1.0\"}"}
                   }
               }
           },
       {
               "PutRequest": {
                   "Item": {
                       "type": {"S":"movie"},
                       "uuid": {"S":"Mermaids (1990)"},
                       "genre": {"S":"Comedy|Drama|Romance"},
                       "movie_ratings": {"S":"{\"156\": \"3.5\", \"275\": \"3.0\", \"307\": \"3.0\", \"599\": \"2.0\", \"600\": \"3.5\", \"606\": \"4.0\"}"}
                   }
               }
           },
       {
               "PutRequest": {
                   "Item": {
                       "type": {"S":"movie"},
                       "uuid": {"S":"Navy Seals (1990)"},
                       "genre": {"S":"Action|Adventure|War"},
                       "movie_ratings": {"S":"{\"42\": \"3.0\", \"422\": \"2.0\", \"438\": \"1.0\"}"}
                   }
               }
           },
       {
               "PutRequest": {
                   "Item": {
                       "type": {"S":"movie"},
                       "uuid": {"S":"Manhunter (1986)"},
                       "genre": {"S":"Action|Crime|Drama|Horror|Thriller"},
                       "movie_ratings": {"S":"{\"313\": \"4.0\", \"387\": \"3.5\", \"414\": \"3.0\", \"474\": \"3.5\", \"532\": \"5.0\", \"562\": \"4.5\"}"}
                   }
               }
           },
       {
               "PutRequest": {
                   "Item": {
                       "type": {"S":"movie"},
                       "uuid": {"S":"Reversal of Fortune (1990)"},
                       "genre": {"S":"Drama"},
                       "movie_ratings": {"S":"{\"28\": \"2.0\", \"74\": \"4.0\", \"275\": \"4.0\", \"387\": \"4.0\", \"462\": \"4.5\", \"474\": \"4.0\"}"}
                   }
               }
           },
       {
               "PutRequest": {
                   "Item": {
                       "type": {"S":"movie"},
                       "uuid": {"S":"Death on the Nile (1978)"},
                       "genre": {"S":"Crime|Mystery"},
                       "movie_ratings": {"S":"{\"448\": \"3.0\"}"}
                   }
               }
           },
       {
               "PutRequest": {
                   "Item": {
                       "type": {"S":"movie"},
                       "uuid": {"S":"Revenge of the Nerds (1984)"},
                       "genre": {"S":"Comedy"},
                       "movie_ratings": {"S":"{\"91\": \"2.0\", \"226\": \"4.0\", \"274\": \"3.5\", \"275\": \"3.0\", \"281\": \"3.0\", \"369\": \"3.0\", \"410\": \"4.0\", \"414\": \"3.0\", \"474\": \"2.0\", \"477\": \"4.0\", \"531\": \"2.0\", \"599\": \"2.5\", \"608\": \"1.5\"}"}
                   }
               }
           },
       {
               "PutRequest": {
                   "Item": {
                       "type": {"S":"movie"},
                       "uuid": {"S":"Revenge of the Nerds II: Nerds in Paradise (1987)"},
                       "genre": {"S":"Comedy"},
                       "movie_ratings": {"S":"{\"51\": \"3.5\", \"226\": \"2.5\", \"414\": \"2.0\", \"474\": \"1.0\", \"514\": \"2.0\", \"599\": \"1.5\"}"}
                   }
               }
           },
       {
               "PutRequest": {
                   "Item": {
                       "type": {"S":"movie"},
                       "uuid": {"S":"4 Little Girls (1997)"},
                       "genre": {"S":"Documentary"},
                       "movie_ratings": {"S":"{\"253\": \"4.5\", \"474\": \"4.0\"}"}
                   }
               }
           },
       {
               "PutRequest": {
                   "Item": {
                       "type": {"S":"movie"},
                       "uuid": {"S":"River\"s Edge (1986)"},
                       "genre": {"S":"Crime|Drama"},
                       "movie_ratings": {"S":"{\"474\": \"3.5\"}"}
                   }
               }
           },
       {
               "PutRequest": {
                   "Item": {
                       "type": {"S":"movie"},
                       "uuid": {"S":"Girls Just Want to Have Fun (1985)"},
                       "genre": {"S":"Comedy"},
                       "movie_ratings": {"S":"{\"220\": \"3.0\", \"414\": \"3.0\", \"562\": \"4.0\"}"}
                   }
               }
           },
       {
               "PutRequest": {
                   "Item": {
                       "type": {"S":"movie"},
                       "uuid": {"S":"Longest Yard, The (1974)"},
                       "genre": {"S":"Comedy"},
                       "movie_ratings": {"S":"{\"36\": \"2.0\", \"140\": \"3.0\", \"226\": \"4.0\", \"414\": \"4.0\", \"422\": \"4.0\"}"}
                   }
               }
           },
       {
               "PutRequest": {
                   "Item": {
                       "type": {"S":"movie"},
                       "uuid": {"S":"Necessary Roughness (1991)"},
                       "genre": {"S":"Comedy"},
                       "movie_ratings": {"S":"{\"414\": \"3.0\", \"448\": \"3.0\", \"474\": \"2.0\", \"590\": \"2.5\"}"}
                   }
               }
           },
       {
               "PutRequest": {
                   "Item": {
                       "type": {"S":"movie"},
                       "uuid": {"S":"Enemy at the Gates (2001)"},
                       "genre": {"S":"Drama|War"},
                       "movie_ratings": {"S":"{\"7\": \"2.0\", \"28\": \"4.0\", \"29\": \"4.0\", \"62\": \"4.5\", \"63\": \"3.5\", \"64\": \"3.5\", \"68\": \"2.5\", \"80\": \"4.0\", \"105\": \"4.0\", \"139\": \"4.0\", \"140\": \"5.0\", \"160\": \"3.0\", \"182\": \"2.0\", \"195\": \"3.0\", \"199\": \"4.0\", \"239\": \"5.0\", \"274\": \"4.0\", \"275\": \"4.0\", \"279\": \"2.5\", \"298\": \"2.5\", \"305\": \"5.0\", \"328\": \"2.5\", \"331\": \"4.0\", \"334\": \"2.5\", \"339\": \"4.5\", \"414\": \"4.0\", \"421\": \"4.0\", \"428\": \"3.0\", \"432\": \"4.5\", \"434\": \"1.5\", \"438\": \"3.5\", \"453\": \"4.0\", \"463\": \"4.0\", \"474\": \"2.0\", \"480\": \"3.0\", \"483\": \"4.0\", \"561\": \"3.5\", \"599\": \"2.5\", \"603\": \"3.0\", \"608\": \"4.5\"}"}
                   }
               }
           },
       {
               "PutRequest": {
                   "Item": {
                       "type": {"S":"movie"},
                       "uuid": {"S":"Exit Wounds (2001)"},
                       "genre": {"S":"Action|Thriller"},
                       "movie_ratings": {"S":"{\"274\": \"2.5\", \"292\": \"3.0\"}"}
                   }
               }
           },
       {
               "PutRequest": {
                   "Item": {
                       "type": {"S":"movie"},
                       "uuid": {"S":"Dish, The (2001)"},
                       "genre": {"S":"Comedy"},
                       "movie_ratings": {"S":"{\"140\": \"5.0\", \"182\": \"4.0\", \"334\": \"3.5\", \"410\": \"4.0\", \"448\": \"4.0\", \"453\": \"4.0\", \"474\": \"3.5\"}"}
                   }
               }
           },
       {
               "PutRequest": {
                   "Item": {
                       "type": {"S":"movie"},
                       "uuid": {"S":"Memento (2000)"},
                       "genre": {"S":"Mystery|Thriller"},
                       "movie_ratings": {"S":"{\"4\": \"2.0\", \"15\": \"1.5\", \"16\": \"4.5\", \"17\": \"4.0\", \"18\": \"4.5\", \"20\": \"3.5\", \"22\": \"3.0\", \"23\": \"4.5\", \"28\": \"3.5\", \"34\": \"4.5\", \"41\": \"4.0\", \"50\": \"3.0\", \"61\": \"4.5\", \"63\": \"3.5\", \"64\": \"4.5\", \"65\": \"4.0\", \"66\": \"5.0\", \"68\": \"4.0\", \"73\": \"4.0\", \"74\": \"4.0\", \"76\": \"4.5\", \"77\": \"2.5\", \"80\": \"5.0\", \"83\": \"4.5\", \"86\": \"4.5\", \"88\": \"4.0\", \"91\": \"4.5\", \"98\": \"4.0\", \"103\": \"5.0\", \"104\": \"4.0\", \"105\": \"3.5\", \"111\": \"3.5\", \"123\": \"4.5\", \"124\": \"4.5\", \"125\": \"4.0\", \"127\": \"2.0\", \"129\": \"3.0\", \"131\": \"4.0\", \"132\": \"4.0\", \"135\": \"5.0\", \"140\": \"3.0\", \"141\": \"3.0\", \"144\": \"5.0\", \"153\": \"4.0\", \"156\": \"4.5\", \"166\": \"5.0\", \"178\": \"4.5\", \"182\": \"4.5\", \"184\": \"5.0\", \"185\": \"5.0\", \"187\": \"4.0\", \"198\": \"4.0\", \"199\": \"4.0\", \"200\": \"4.0\", \"204\": \"4.5\", \"211\": \"4.5\", \"215\": \"4.0\", \"219\": \"5.0\", \"220\": \"5.0\", \"223\": \"4.0\", \"232\": \"5.0\", \"234\": \"4.0\", \"246\": \"5.0\", \"247\": \"4.5\", \"249\": \"5.0\", \"254\": \"4.5\", \"260\": \"4.0\", \"263\": \"5.0\", \"274\": \"4.5\", \"275\": \"5.0\", \"279\": \"3.0\", \"282\": \"4.5\", \"286\": \"4.5\", \"288\": \"4.5\", \"295\": \"4.5\", \"298\": \"3.0\", \"301\": \"4.0\", \"305\": \"3.5\", \"307\": \"4.0\", \"308\": \"1.0\", \"313\": \"4.0\", \"318\": \"4.0\", \"322\": \"3.5\", \"325\": \"4.0\", \"326\": \"3.5\", \"327\": \"4.5\", \"330\": \"5.0\", \"332\": \"5.0\", \"334\": \"3.5\", \"339\": \"4.5\", \"343\": \"5.0\", \"344\": \"1.5\", \"348\": \"5.0\", \"351\": \"4.0\", \"352\": \"5.0\", \"356\": \"5.0\", \"365\": \"0.5\", \"369\": \"4.5\", \"370\": \"3.5\", \"371\": \"4.5\", \"375\": \"5.0\", \"376\": \"5.0\", \"378\": \"3.5\", \"380\": \"5.0\", \"381\": \"4.5\", \"382\": \"5.0\", \"387\": \"4.5\", \"390\": \"4.5\", \"391\": \"5.0\", \"393\": \"5.0\", \"405\": \"4.5\", \"414\": \"5.0\", \"415\": \"4.5\", \"417\": \"5.0\", \"418\": \"3.5\", \"419\": \"3.0\", \"424\": \"4.5\", \"425\": \"3.5\", \"426\": \"2.0\", \"427\": \"5.0\", \"432\": \"3.5\", \"434\": \"5.0\", \"438\": \"4.5\", \"448\": \"4.0\", \"449\": \"4.5\", \"453\": \"5.0\", \"464\": \"4.0\", \"472\": \"1.0\", \"474\": \"5.0\", \"477\": \"4.0\", \"480\": \"4.0\", \"483\": \"4.0\", \"489\": \"4.5\", \"490\": \"4.0\", \"503\": \"4.0\", \"505\": \"5.0\", \"522\": \"3.5\", \"525\": \"4.0\", \"542\": \"5.0\", \"543\": \"5.0\", \"549\": \"5.0\", \"551\": \"3.0\", \"560\": \"3.5\", \"567\": \"3.5\", \"570\": \"4.0\", \"573\": \"5.0\", \"580\": \"5.0\", \"581\": \"4.5\", \"582\": \"4.0\", \"590\": \"3.5\", \"596\": \"4.5\", \"598\": \"1.0\", \"599\": \"4.5\", \"600\": \"4.0\", \"601\": \"5.0\", \"603\": \"5.0\", \"606\": \"4.0\", \"608\": \"4.5\", \"610\": \"5.0\"}"}
                   }
               }
           },
       {
               "PutRequest": {
                   "Item": {
                       "type": {"S":"movie"},
                       "uuid": {"S":"Heartbreakers (2001)"},
                       "genre": {"S":"Comedy|Crime|Romance"},
                       "movie_ratings": {"S":"{\"111\": \"2.5\", \"160\": \"1.0\", \"185\": \"2.0\", \"298\": \"3.0\", \"307\": \"0.5\", \"387\": \"2.0\", \"414\": \"3.0\", \"428\": \"2.0\", \"438\": \"2.5\", \"610\": \"3.0\"}"}
                   }
               }
           },
       {
               "PutRequest": {
                   "Item": {
                       "type": {"S":"movie"},
                       "uuid": {"S":"Say It Isn\"t So (2001)"},
                       "genre": {"S":"Comedy|Romance"},
                       "movie_ratings": {"S":"{\"226\": \"1.0\", \"307\": \"1.5\", \"414\": \"3.0\", \"448\": \"3.0\"}"}
                   }
               }
           },
       {
               "PutRequest": {
                   "Item": {
                       "type": {"S":"movie"},
                       "uuid": {"S":"Someone Like You (2001)"},
                       "genre": {"S":"Comedy|Romance"},
                       "movie_ratings": {"S":"{\"66\": \"3.5\", \"182\": \"3.5\", \"357\": \"4.5\", \"414\": \"3.0\", \"438\": \"3.0\"}"}
                   }
               }
           },
       {
               "PutRequest": {
                   "Item": {
                       "type": {"S":"movie"},
                       "uuid": {"S":"Spy Kids (2001)"},
                       "genre": {"S":"Action|Adventure|Children|Comedy"},
                       "movie_ratings": {"S":"{\"20\": \"0.5\", \"103\": \"2.5\", \"156\": \"3.0\", \"177\": \"2.5\", \"186\": \"5.0\", \"232\": \"2.5\", \"234\": \"4.0\", \"256\": \"3.0\", \"274\": \"3.5\", \"280\": \"1.5\", \"292\": \"4.0\", \"305\": \"3.0\", \"380\": \"3.0\", \"381\": \"3.5\", \"414\": \"4.0\", \"430\": \"3.0\", \"448\": \"2.0\", \"466\": \"3.5\", \"474\": \"4.0\", \"475\": \"4.5\", \"503\": \"0.5\", \"525\": \"3.5\", \"527\": \"4.0\", \"560\": \"2.5\", \"600\": \"3.5\", \"603\": \"1.0\", \"606\": \"1.5\", \"610\": \"3.5\"}"}
                   }
               }
           },
       {
               "PutRequest": {
                   "Item": {
                       "type": {"S":"movie"},
                       "uuid": {"S":"Tomcats (2001)"},
                       "genre": {"S":"Comedy"},
                       "movie_ratings": {"S":"{\"226\": \"0.5\", \"274\": \"3.5\", \"387\": \"0.5\", \"414\": \"2.0\", \"448\": \"2.5\", \"453\": \"3.0\"}"}
                   }
               }
           },
       {
               "PutRequest": {
                   "Item": {
                       "type": {"S":"movie"},
                       "uuid": {"S":"Tailor of Panama, The (2001)"},
                       "genre": {"S":"Drama|Thriller"},
                       "movie_ratings": {"S":"{\"140\": \"3.0\", \"182\": \"3.0\", \"414\": \"3.0\", \"448\": \"3.0\", \"453\": \"4.0\"}"}
                   }
               }
           },
       {
               "PutRequest": {
                   "Item": {
                       "type": {"S":"movie"},
                       "uuid": {"S":"Amores Perros (Love\"s a Bitch) (2000)"},
                       "genre": {"S":"Drama|Thriller"},
                       "movie_ratings": {"S":"{\"23\": \"4.0\", \"41\": \"4.0\", \"64\": \"5.0\", \"95\": \"5.0\", \"132\": \"2.0\", \"178\": \"4.0\", \"182\": \"5.0\", \"198\": \"4.0\", \"241\": \"3.0\", \"260\": \"3.5\", \"275\": \"5.0\", \"312\": \"3.0\", \"326\": \"4.0\", \"334\": \"3.5\", \"387\": \"4.5\", \"391\": \"2.0\", \"414\": \"4.0\", \"432\": \"4.0\", \"453\": \"5.0\", \"489\": \"4.0\", \"580\": \"4.0\", \"600\": \"3.0\", \"603\": \"5.0\"}"}
                   }
               }
           },
       {
               "PutRequest": {
                   "Item": {
                       "type": {"S":"movie"},
                       "uuid": {"S":"Keep the River on Your Right: A Modern Cannibal Tale (2000)"},
                       "genre": {"S":"Documentary"},
                       "movie_ratings": {"S":"{\"462\": \"3.5\"}"}
                   }
               }
           }
   ]
}